<xml xmlns="https://developers.google.com/blockly/xml"><variables><variable id="QyX,MQ=_G/9gK]+Na5y+">data</variable><variable id="oyZ.AaTkf|.tHwdH$$!g">text</variable><variable id="r|[66P)d@VT.UBC;O`S-">low</variable><variable id="=[0ur:^..h8hS=Zh@OLI">high</variable></variables><block type="variables_def" id="r,9*=LmnX@3{}L%#k#zU" x="-28" y="58"><mutation xmlns="http://www.w3.org/1999/xhtml" no_input="false" variable_uuid="6569cbda-2075-43cf-a979-c508d1d91c28" variable_name="PF_isEditing" variable_scope="APP"/><field name="SCOPE">APP</field><field name="NAME">PF_isEditing</field><value name="VALUE"><block type="logic_boolean" id="T=gnv(5RbrsS(LVe{oxE"><field name="BOOL">TRUE</field></block></value></block><block type="variables_when_changes" id="oX/qfR!p`?YgF),}OHu%" x="549" y="58"><field name="VAR">6569cbda-2075-43cf-a979-c508d1d91c28</field><statement name="DO"><block type="setter" id="xM7MU%w.{fviwb/?%4M?"><mutation xmlns="http://www.w3.org/1999/xhtml" component_name="PF_ErrorLabel" parent_id="undefined"/><field name="component_id">bbf55e4d-72d2-40d0-8adf-3673b11fad6f</field><field name="field_name">Text</field><value name="field_value"><shadow type="text" id="=!=#BVn%J%F_]@=RlG0C"><field name="TEXT"/></shadow></value><next><block type="setter" id="ge~gGuI~X(PtI1:cTi(V"><mutation xmlns="http://www.w3.org/1999/xhtml" component_name="Profile_Preview" parent_id="undefined"/><field name="component_id">d8982511-91b0-4133-bbc6-f69736e531ba</field><field name="field_name">Visible</field><value name="field_value"><shadow type="logic_boolean" id="c]]?x-;V`-otmHMmZFRo"><field name="BOOL">FALSE</field></shadow></value><next><block type="setter" id="L,#PwF:)xl$^9gL@@.Mj"><mutation xmlns="http://www.w3.org/1999/xhtml" component_name="Profile_Edit" parent_id="undefined"/><field name="component_id">acb79f9c-a5c8-435e-a45a-62d7bd896ffb</field><field name="field_name">Visible</field><value name="field_value"><shadow type="logic_boolean" id="XKh0h9D#=CIZ$^M3pK4#"><field name="BOOL">FALSE</field></shadow></value><next><block type="controls_if" id="=o?/Bm+Ij-K*-Qg%SljQ"><mutation else="1"/><value name="IF0"><block type="variables_get" id="Ksy.@x/Q#.BJRS`6/rXj"><mutation xmlns="http://www.w3.org/1999/xhtml" saved_name="app variable PF_isEditing"/><field name="VAR">6569cbda-2075-43cf-a979-c508d1d91c28</field></block></value><statement name="DO0"><block type="setter" id="-lRk0P{!KE|0my!*;yh{"><mutation xmlns="http://www.w3.org/1999/xhtml" component_name="PF_Name_2" parent_id="undefined"/><field name="component_id">235d5723-0b5d-4ec9-8e29-1fa651243644</field><field name="field_name">Text</field><value name="field_value"><shadow type="text" id="UGv~cp|K%1Dw8z*P_azZ"><field name="TEXT"/></shadow><block type="set_get" id="2$ASa]DA=u:=BH[d7j0("><mutation xmlns="http://www.w3.org/1999/xhtml" component_name="PF_Name_1" parent_id="undefined"/><field name="component_id">ae137b62-dd67-42b7-8d28-d2681f8753bd</field><field name="field_name">Text</field></block></value><next><block type="setter" id="=+ZQQOtyKmDHn9Gs02P#"><mutation xmlns="http://www.w3.org/1999/xhtml" component_name="PF_Phone_2" parent_id="undefined"/><field name="component_id">c1445a20-a8bf-4193-b8b3-e912585aef7c</field><field name="field_name">Text</field><value name="field_value"><shadow type="text" id="_yh@7a`S8qCoEa2O=:|r"><field name="TEXT"/></shadow><block type="set_get" id="x:q4i)1JRozJs*4{)`aj"><mutation xmlns="http://www.w3.org/1999/xhtml" component_name="PF_Phone_1" parent_id="undefined"/><field name="component_id">9c042b51-d119-47cd-b826-342ef51a65ed</field><field name="field_name">Text</field></block></value><next><block type="setter" id="(.q0)0Oc(C|K`_`xYO]Q"><mutation xmlns="http://www.w3.org/1999/xhtml" component_name="Profile_Edit" parent_id="undefined"/><field name="component_id">acb79f9c-a5c8-435e-a45a-62d7bd896ffb</field><field name="field_name">Visible</field><value name="field_value"><shadow type="logic_boolean" id="i{i-T3es14mnv^_TQ_js"><field name="BOOL">TRUE</field></shadow></value></block></next></block></next></block></statement><statement name="ELSE"><block type="setter" id="UGmV*G+VoNZFF[|aEkX$"><mutation xmlns="http://www.w3.org/1999/xhtml" component_name="PF_Name_1" parent_id="undefined"/><field name="component_id">ae137b62-dd67-42b7-8d28-d2681f8753bd</field><field name="field_name">Text</field><value name="field_value"><shadow type="text" id="PYjM+StX%/Dp34z5D[1U"><field name="TEXT">Label</field></shadow><block type="variables_get_dynamic" id="ddPped;^I-j5OEI`yM=#"><field name="SCOPE">CLOUD</field><value name="NAME"><shadow type="text" id="vDSloy25p8+`8R/cX|a5"><field name="TEXT">name</field></shadow><block type="procedures_callasyncreturn" id="(fFsObKtGdSAEIk:q2pf"><mutation name="profileData"><arg name="data"/></mutation><value name="ARG0"><block type="text" id="$JSpoxC@|IVPsr(=Idj:"><field name="TEXT">Name</field></block></value></block></value></block></value><next><block type="setter" id="g!iU6p4Uvd$eCpH.upHS"><mutation xmlns="http://www.w3.org/1999/xhtml" component_name="PF_Phone_1" parent_id="undefined"/><field name="component_id">9c042b51-d119-47cd-b826-342ef51a65ed</field><field name="field_name">Text</field><value name="field_value"><shadow type="text" id="RcrYe!u1K={^M6Ov89e6"><field name="TEXT">Label</field></shadow><block type="variables_get_dynamic" id="1e+[!dj;wt.:kK8jZ[@h"><field name="SCOPE">CLOUD</field><value name="NAME"><shadow type="text" id="vDSloy25p8+`8R/cX|a5"><field name="TEXT">name</field></shadow><block type="procedures_callasyncreturn" id="jNtufnl2{dC5BR|^T4;("><mutation name="profileData"><arg name="data"/></mutation><value name="ARG0"><block type="text" id="@Bk?:K42awZ7sWmN9+tv"><field name="TEXT">Phone</field></block></value></block></value></block></value><next><block type="controls_if" id="=7=^:oDry6S|o^{7fSgT"><value name="IF0"><block type="logic_compare" id="(p4s{{K^2`t1gl!2NO0+"><field name="OP">EQ</field><value name="A"><block type="set_get" id="_R3mGTW;YNXns3h.wnQ`"><mutation xmlns="http://www.w3.org/1999/xhtml" component_name="PF_Name_1" parent_id="undefined"/><field name="component_id">ae137b62-dd67-42b7-8d28-d2681f8753bd</field><field name="field_name">Text</field></block></value><value name="B"><block type="text" id="bwGW:Y21I)DvQ9{b#npq"><field name="TEXT">null</field></block></value></block></value><statement name="DO0"><block type="setter" id="0IT+y%j3FWzUw+]usMsz"><mutation xmlns="http://www.w3.org/1999/xhtml" component_name="PF_Name_1" parent_id="undefined"/><field name="component_id">ae137b62-dd67-42b7-8d28-d2681f8753bd</field><field name="field_name">Text</field><value name="field_value"><shadow type="text" id="PYjM+StX%/Dp34z5D[1U"><field name="TEXT"/></shadow></value></block></statement><next><block type="controls_if" id="G}X1sG9cjo;QZDMx%fzs"><value name="IF0"><block type="logic_compare" id=".d5?$`PE[t@+W;wNoI~O"><field name="OP">EQ</field><value name="A"><block type="set_get" id="m;?ekP8S2buOX-_X^Z(X"><mutation xmlns="http://www.w3.org/1999/xhtml" component_name="PF_Phone_1" parent_id="undefined"/><field name="component_id">9c042b51-d119-47cd-b826-342ef51a65ed</field><field name="field_name">Text</field></block></value><value name="B"><block type="text" id="UUmMxE_xqgvY=JQ%4!D}"><field name="TEXT">null</field></block></value></block></value><statement name="DO0"><block type="setter" id="Fp1S4Xwh#7|XyJ9ec5oC"><mutation xmlns="http://www.w3.org/1999/xhtml" component_name="PF_Phone_1" parent_id="undefined"/><field name="component_id">9c042b51-d119-47cd-b826-342ef51a65ed</field><field name="field_name">Text</field><value name="field_value"><shadow type="text" id="!S0w1U,_dfIzm8rbY(]a"><field name="TEXT"/></shadow></value></block></statement><next><block type="setter" id="Gl=qJPzoDvn7y+XeMU%L"><mutation xmlns="http://www.w3.org/1999/xhtml" component_name="Profile_Preview" parent_id="undefined"/><field name="component_id">d8982511-91b0-4133-bbc6-f69736e531ba</field><field name="field_name">Visible</field><value name="field_value"><shadow type="logic_boolean" id="AQcCy]n5iJ2J`bggl@z6"><field name="BOOL">TRUE</field></shadow></value></block></next></block></next></block></next></block></next></block></statement></block></next></block></next></block></next></block></statement></block><block type="component_event" id="xFlzwdgj_4mXo:hUpX!;" x="-27" y="139"><mutation xmlns="http://www.w3.org/1999/xhtml" component_name="Profile Information" component_type="Screen" parent_id="undefined" event_id="Opens" was_updated="true"/><field name="component_id">fd1ebf5c-e2f6-4d3e-9dc8-a5f1a5d32345</field><field name="event_id">Opens</field><statement name="input_do"><block type="setter" id="tf:DroU]gr-GK|,hG}IX"><mutation xmlns="http://www.w3.org/1999/xhtml" component_name="PF_Email" parent_id="undefined"/><field name="component_id">e8a44b59-b23e-4e48-8e25-5f6b78cc16ec</field><field name="field_name">Text</field><value name="field_value"><shadow type="text" id="Fp_=U:0HT-Hz4K*yE!z+"><field name="TEXT">Label</field></shadow><block type="variables_get" id="1@g]zA;dT,R}6V/SACKa"><mutation xmlns="http://www.w3.org/1999/xhtml" saved_name="app variable session email"/><field name="VAR">aff394d4-2841-4812-b424-d51b5fa39b25</field></block></value><next><block type="variables_set" id="{W+OnYf#gG.yLyvfylxT"><mutation xmlns="http://www.w3.org/1999/xhtml" saved_name="app variable PF_isEditing"/><field name="VAR">6569cbda-2075-43cf-a979-c508d1d91c28</field><value name="VALUE"><block type="logic_boolean" id="^SxaP(QX$^?V@+(ij4#O"><field name="BOOL">FALSE</field></block></value></block></next></block></statement></block><block type="component_event" id="#Ujj7BHYU`Qy)yA(3}:r" x="-27" y="339"><mutation xmlns="http://www.w3.org/1999/xhtml" component_name="PF_SignOut" component_type="Button" parent_id="undefined" event_id="Click" was_updated="true"/><field name="component_id">1f24004f-5b4f-4ffa-a8ef-9f47a6e53a24</field><field name="event_id">Click</field><statement name="input_do"><block type="signin_sign_out_advanced" id="JEbj@yth#cSpE)]#C+7e" inline="false"><mutation xmlns="http://www.w3.org/1999/xhtml" show_callback_params="true" callback_params_added="true"/><value name="CALLBACK_PARAM0"><block type="callback_arg" id="Vmx:l#f=H}ss{dW3G;MI"><mutation xmlns="http://www.w3.org/1999/xhtml" tooltip="" language_neutral_name="error" arg_name_trans_key="blocks.signin.error" old_arg_name="error"/></block></value><statement name="DO"><block type="setter" id="Q-wIz`qkoFE:Y,s5)cfM"><mutation xmlns="http://www.w3.org/1999/xhtml" component_name="PF_ErrorLabel" parent_id="undefined"/><field name="component_id">bbf55e4d-72d2-40d0-8adf-3673b11fad6f</field><field name="field_name">Text</field><value name="field_value"><shadow type="text" id="-F;DKT)}LYo~6kAAve~5"><field name="TEXT">Label</field></shadow><block type="callback_arg" id="$p%_%+j%l{!5sK=62|Vx"><mutation xmlns="http://www.w3.org/1999/xhtml" tooltip="" language_neutral_name="error" arg_name_trans_key="blocks.signin.error" old_arg_name="error" is_detached_parameter="true"/></block></value></block></statement><next><block type="controls_navigate_new" id="`bh}WoUPe@).*LLB]c}n"><value name="COMPONENT"><shadow type="any_component_component_dropdown" id="ScWx]JR,,%Mhk4|Is_t["><mutation xmlns="http://www.w3.org/1999/xhtml" component_id="LoginScreen" component_types_to_include="[&quot;Screen&quot;]"/><field name="component_id">7acf995d-cc1c-4383-a94b-e69798ec842b</field></shadow></value></block></next></block></statement></block><block type="procedures_defasyncreturn" id="KMIVX,_7]/V/{u!:O~~B" x="-27" y="565"><mutation><arg name="data" varid="QyX,MQ=_G/9gK]+Na5y+"/></mutation><field name="NAME">profileData</field><comment pinned="false" h="80" w="160">Describe this function...</comment><statement name="STACK"><block type="procedures_return" id="=PUWLEjU,=-jk!7)G(GT"><mutation xmlns="http://www.w3.org/1999/xhtml" value="1"/><value name="VALUE"><block type="text_join" id="KOF8#-Z$ZU?Hx]ffRo+W"><mutation items="4"/><value name="ADD0"><block type="text" id="hnm}Za,c`sy(u7W4+ke;"><field name="TEXT">Users/</field></block></value><value name="ADD1"><block type="variables_get" id="L2-qY:1)c;,Xt`fN6?Op"><mutation xmlns="http://www.w3.org/1999/xhtml" saved_name="app variable user ID"/><field name="VAR">236afda8-d250-4fc5-85d6-0d55d7532c93</field></block></value><value name="ADD2"><block type="text" id="+@%kRR~lCG#E_?|%@PU3"><field name="TEXT">/</field></block></value><value name="ADD3"><block type="variables_get" id=")S@b?PqKly^{,2!;:9sq"><mutation xmlns="http://www.w3.org/1999/xhtml" saved_name="data"/><field name="VAR" id="QyX,MQ=_G/9gK]+Na5y+">data</field></block></value></block></value></block></statement></block><block type="component_event" id="gN!{y=*o$,,Odb0oS7w1" x="550" y="638"><mutation xmlns="http://www.w3.org/1999/xhtml" component_name="PF_Edit_1" component_type="Button" parent_id="undefined" event_id="Click" was_updated="true"/><field name="component_id">444537ce-9494-4ad9-aeff-f28a074c421f</field><field name="event_id">Click</field><statement name="input_do"><block type="variables_set" id="Y47`79Gl+a`$`dNN,0tp"><mutation xmlns="http://www.w3.org/1999/xhtml" saved_name="app variable PF_isEditing"/><field name="VAR">6569cbda-2075-43cf-a979-c508d1d91c28</field><value name="VALUE"><block type="logic_boolean" id="Hr,o7gEilB/}YiY8!XOL"><field name="BOOL">TRUE</field></block></value></block></statement></block><block type="procedures_defasyncreturn" id="PKD2x!@~v`D}9uG.3ksx" x="-27" y="771"><mutation><arg name="text" varid="oyZ.AaTkf|.tHwdH$$!g"/></mutation><field name="NAME">isNumber</field><comment pinned="false" h="80" w="160">Describe this function...</comment><statement name="STACK"><block type="procedures_return" id="IK)__N2_;aqnH~#~j]N_"><mutation xmlns="http://www.w3.org/1999/xhtml" value="1"/><value name="VALUE"><block type="logic_operation" id="-,ONgF/Aqo]E/02itu]#"><field name="OP">OR</field><value name="A"><block type="math_number_property" id="vPcwD,-#7$FXPZec|J{$"><mutation divisor_input="false"/><field name="PROPERTY">EVEN</field><value name="NUMBER_TO_CHECK"><shadow type="math_number" id="rPOE]*J2R,%#~IWRe.e{"><field name="NUM">0</field></shadow><block type="variables_get" id="nE3#,8/y^mEwv*$ms]HR"><mutation xmlns="http://www.w3.org/1999/xhtml" saved_name="text"/><field name="VAR" id="oyZ.AaTkf|.tHwdH$$!g">text</field></block></value></block></value><value name="B"><block type="math_number_property" id="SeS}9,-hZRL5yXf+lB-1"><mutation divisor_input="false"/><field name="PROPERTY">ODD</field><value name="NUMBER_TO_CHECK"><shadow type="math_number" id="t*CJ|Bj}MX-8n!nTW;rJ"><field name="NUM">0</field></shadow><block type="variables_get" id="aIpqrK1DXo`m|b{Fi7o,"><mutation xmlns="http://www.w3.org/1999/xhtml" saved_name="text"/><field name="VAR" id="oyZ.AaTkf|.tHwdH$$!g">text</field></block></value></block></value></block></value></block></statement></block><block type="component_event" id="!2vdZ4q@|8;Jo(56BU6I" x="550" y="761"><mutation xmlns="http://www.w3.org/1999/xhtml" component_name="PF_Save_2" component_type="Button" parent_id="undefined" event_id="Click" was_updated="true"/><field name="component_id">d9fc9f1c-2f8f-405c-b223-36b442ef74fa</field><field name="event_id">Click</field><statement name="input_do"><block type="controls_if" id="Fvu)(8).p~PQy(!.cb*?"><mutation else="1"/><value name="IF0"><block type="logic_operation" id="$Li~VGGS/[V5Vqm/mNA?"><field name="OP">OR</field><value name="A"><block type="text_isEmpty" id="WDs`mf{KFF}efKK$f:Hy"><value name="VALUE"><shadow type="text" id="xof~ZmIC)cOp~sGvX_I{"><field name="TEXT"/></shadow><block type="set_get" id="QB$yi.Q$sV0S5s]!LHox"><mutation xmlns="http://www.w3.org/1999/xhtml" component_name="PF_Phone_2" parent_id="undefined"/><field name="component_id">c1445a20-a8bf-4193-b8b3-e912585aef7c</field><field name="field_name">Text</field></block></value></block></value><value name="B"><block type="procedures_callasyncreturn" id="1-b^8!E!UW5/dO=F[.*l"><mutation name="inRange"><arg name="text"/><arg name="low"/><arg name="high"/></mutation><value name="ARG0"><block type="set_get" id="WEy|2/tGL//w~wfcapXX"><mutation xmlns="http://www.w3.org/1999/xhtml" component_name="PF_Phone_2" parent_id="undefined"/><field name="component_id">c1445a20-a8bf-4193-b8b3-e912585aef7c</field><field name="field_name">Text</field></block></value><value name="ARG1"><block type="math_number" id="[hNvA@z5b^lWrzo1D*o{"><field name="NUM">0</field></block></value><value name="ARG2"><block type="math_number" id=",B/D.-6w1W0Um{C++o?5"><field name="NUM">9999999999</field></block></value></block></value></block></value><statement name="DO0"><block type="variables_set_dynamic" id="AdJ[tn.tS}|rbqG[gqE+"><field name="SCOPE">CLOUD</field><value name="NAME"><shadow type="text" id="(HgMXPA)x*vo+}pPZLGH"><field name="TEXT">name</field></shadow><block type="procedures_callasyncreturn" id="?NI{,r@gyr[+-zK^TX,u"><mutation name="profileData"><arg name="data"/></mutation><value name="ARG0"><block type="text" id="(b;h3:2LHwB:8Lp0~pLX"><field name="TEXT">Name</field></block></value></block></value><value name="VALUE"><block type="set_get" id="FnHS..I/rJV`_vv+Lg)T"><mutation xmlns="http://www.w3.org/1999/xhtml" component_name="PF_Name_2" parent_id="undefined"/><field name="component_id">235d5723-0b5d-4ec9-8e29-1fa651243644</field><field name="field_name">Text</field></block></value><next><block type="variables_set_dynamic" id="0_4!4)s*X,Z(!{c.!EI7"><field name="SCOPE">CLOUD</field><value name="NAME"><shadow type="text" id="(HgMXPA)x*vo+}pPZLGH"><field name="TEXT">name</field></shadow><block type="procedures_callasyncreturn" id="w1sCh6V.Bc5Bgf)2{L:^"><mutation name="profileData"><arg name="data"/></mutation><value name="ARG0"><block type="text" id="f*!#yYtrsx:$7}E;GP~4"><field name="TEXT">Phone</field></block></value></block></value><value name="VALUE"><block type="set_get" id="cAi)O]6jf6wVU,CZ$f4h"><mutation xmlns="http://www.w3.org/1999/xhtml" component_name="PF_Phone_2" parent_id="undefined"/><field name="component_id">c1445a20-a8bf-4193-b8b3-e912585aef7c</field><field name="field_name">Text</field></block></value><next><block type="variables_set" id="W21,4{,8dOjZON~n$ub:"><mutation xmlns="http://www.w3.org/1999/xhtml" saved_name="app variable PF_isEditing"/><field name="VAR">6569cbda-2075-43cf-a979-c508d1d91c28</field><value name="VALUE"><block type="logic_boolean" id="WywCb/9YoZ9J_m~iaS5H"><field name="BOOL">FALSE</field></block></value></block></next></block></next></block></statement><statement name="ELSE"><block type="setter" id="2UXv[a_1.dX$uI$wOAEh"><mutation xmlns="http://www.w3.org/1999/xhtml" component_name="PF_ErrorLabel" parent_id="undefined"/><field name="component_id">bbf55e4d-72d2-40d0-8adf-3673b11fad6f</field><field name="field_name">Text</field><value name="field_value"><shadow type="text" id=";dn%X{Yq*?U@Fivip#D@"><field name="TEXT">Please enter a valid phone number</field></shadow></value></block></statement></block></statement></block><block type="procedures_defasyncreturn" id="/i9PndrQ~yZD5ZD,+qN|" x="-26" y="928"><mutation><arg name="text" varid="oyZ.AaTkf|.tHwdH$$!g"/><arg name="low" varid="r|[66P)d@VT.UBC;O`S-"/><arg name="high" varid="=[0ur:^..h8hS=Zh@OLI"/></mutation><field name="NAME">inRange</field><comment pinned="false" h="80" w="160">Describe this function...</comment><statement name="STACK"><block type="controls_if" id="yoC]:wsrp+2X*]x..81/"><value name="IF0"><block type="logic_negate" id="Vs`M2_%IB/2}VOh~8+};"><value name="BOOL"><block type="procedures_callasyncreturn" id="4N|Yk}rUz,XqG1kT|8./"><mutation name="isNumber"><arg name="text"/></mutation><value name="ARG0"><block type="variables_get" id="p=$VtF?|kzs2Ue.snbJY"><mutation xmlns="http://www.w3.org/1999/xhtml" saved_name="text"/><field name="VAR" id="oyZ.AaTkf|.tHwdH$$!g">text</field></block></value></block></value></block></value><statement name="DO0"><block type="procedures_return" id="TVox2Ew|3GY.t6_SPtN8"><mutation xmlns="http://www.w3.org/1999/xhtml" value="1"/><value name="VALUE"><block type="logic_boolean" id="@0Kqi[%vJB1C!K=/vU!]"><field name="BOOL">FALSE</field></block></value></block></statement><next><block type="controls_if" id="J*i!XmI!LuPwTzuH.9?8"><value name="IF0"><block type="logic_compare" id="Q0hTJN-Ggk=vR0eDhTHd"><field name="OP">LT</field><value name="A"><block type="variables_get" id="f-I^%kKZ@^q-EfroRRAt"><mutation xmlns="http://www.w3.org/1999/xhtml" saved_name="text"/><field name="VAR" id="oyZ.AaTkf|.tHwdH$$!g">text</field></block></value><value name="B"><block type="variables_get" id="mCQjBFuz$J}p)G2+F}Cf"><mutation xmlns="http://www.w3.org/1999/xhtml" saved_name="text"/><field name="VAR" id="r|[66P)d@VT.UBC;O`S-">low</field></block></value></block></value><statement name="DO0"><block type="procedures_return" id="J%97]f+;QbA0PlGO$9D+"><mutation xmlns="http://www.w3.org/1999/xhtml" value="1"/><value name="VALUE"><block type="logic_boolean" id="7R-6xtAaz4J.e`U2isMk"><field name="BOOL">FALSE</field></block></value></block></statement><next><block type="controls_if" id="m}Y*GA~sgYEjXh2KtppP"><value name="IF0"><block type="logic_compare" id="*-lUKJE#0+/%GK^||2s#"><field name="OP">GT</field><value name="A"><block type="variables_get" id="BG[_-P$*~l|Nbi[gx)8y"><mutation xmlns="http://www.w3.org/1999/xhtml" saved_name="text"/><field name="VAR" id="oyZ.AaTkf|.tHwdH$$!g">text</field></block></value><value name="B"><block type="variables_get" id="Q*J(A3hvSjX?{t1$WBHR"><mutation xmlns="http://www.w3.org/1999/xhtml" saved_name="text"/><field name="VAR" id="=[0ur:^..h8hS=Zh@OLI">high</field></block></value></block></value><statement name="DO0"><block type="procedures_return" id="9~+YLt%Y}.WR32]6KSxV"><mutation xmlns="http://www.w3.org/1999/xhtml" value="1"/><value name="VALUE"><block type="logic_boolean" id="QTI~rd/^0R%WHWU8nYuy"><field name="BOOL">FALSE</field></block></value></block></statement><next><block type="procedures_return" id="m/wI`Xi.Ul`W{G~0t@!d"><mutation xmlns="http://www.w3.org/1999/xhtml" value="1"/><value name="VALUE"><block type="logic_boolean" id="wqW9E]=LBW9N^AjF7NcV"><field name="BOOL">TRUE</field></block></value></block></next></block></next></block></next></block></statement></block></xml>